[{"time": "2022-11-28 21:31:47", "stage": "stage2", "score": 2520, "acc": 0.81}, {"time": "2022-11-28 21:32:04", "stage": "stage3", "score": 4140, "acc": 0.88}, {"time": "2022-11-28 22:26:52", "stage": "stage1", "score": 1320, "acc": 0.21}, {"time": "2022-11-28 22:27:21", "stage": "stage1", "score": 4550, "acc": 0.79}, {"time": "2022-11-29 08:29:09", "stage": "stage3", "score": 4860, "acc": 1.0}, {"time": "2022-11-29 08:35:43", "stage": "stage2", "score": 2010, "acc": 0.62}, {"time": "2022-11-29 08:35:51", "stage": "stage3", "score": 4860, "acc": 1.0}, {"time": "2022-11-29 08:36:18", "stage": "stage2", "score": 2110, "acc": 0.69}, {"time": "2022-11-29 08:36:34", "stage": "stage2", "score": 3120, "acc": 0.94}, {"time": "2022-11-29 09:14:34", "stage": "stage1", "score": 310, "acc": 0.04}]